SentenceBertService/PytorchLightingService.py
SentenceBertService/__init__.py
SentenceBertService/bentoml.yml
SentenceBertService/artifacts/__init__.py
SentenceBertService/artifacts/model.pt
SentenceBertService/artifacts/tokenizer/__init__.py
SentenceBertService/artifacts/tokenizer/special_tokens_map.json
SentenceBertService/artifacts/tokenizer/tokenizer.json
SentenceBertService/artifacts/tokenizer/tokenizer_config.json
SentenceBertService/artifacts/tokenizer/tokenizer_type.txt
SentenceBertService/artifacts/tokenizer/vocab.txt
SentenceBertService-20211205152102.dist-info/METADATA
SentenceBertService-20211205152102.dist-info/WHEEL
SentenceBertService-20211205152102.dist-info/entry_points.txt
SentenceBertService-20211205152102.dist-info/top_level.txt
SentenceBertService-20211205152102.dist-info/RECORD
