Metadata-Version: 2.1
Name: SentenceBertService
Version: 20211205152102
Summary: BentoML generated model module
Home-page: https://github.com/bentoml/BentoML
License: UNKNOWN
Platform: UNKNOWN
Requires-Dist: bentoml (==0.13.1)
Requires-Dist: torch (==1.10.0)
Requires-Dist: tkitbentomlframeworksexpand (==0.0.0.216386886)
